fgmkr/__init__.py
fgmkr-0.4.21.dist-info/LICENSE.txt
fgmkr-0.4.21.dist-info/METADATA
fgmkr-0.4.21.dist-info/WHEEL
fgmkr-0.4.21.dist-info/top_level.txt
fgmkr-0.4.21.dist-info/RECORD
