Metadata-Version: 2.2
Name: fgmkr
Version: 0.4.21
Summary: Custom Figure Auto Formatter
Author: Chickenfysh
Author-email: iamchicken_3401@outlook.com
Classifier: Programming Language :: Python :: 3
Classifier: License :: OSI Approved :: MIT License
Classifier: Operating System :: OS Independent
License-File: LICENSE.txt
Dynamic: author
Dynamic: author-email
Dynamic: classifier
Dynamic: description
Dynamic: description-content-type
Dynamic: summary
